unlockedpd/__init__.py
unlockedpd/_compat.py
unlockedpd/_config.py
unlockedpd/_patch.py
unlockedpd/_warmup.py
unlockedpd/ops/__init__.py
unlockedpd/ops/_minmax_deque.py
unlockedpd/ops/_welford.py
unlockedpd/ops/agg.py
unlockedpd/ops/aggregations.py
unlockedpd/ops/aggregations.py.backup
unlockedpd/ops/apply.py
unlockedpd/ops/cumulative.py
unlockedpd/ops/dataframe_pairwise.py
unlockedpd/ops/dataframe_transform.py
unlockedpd/ops/ewm.py
unlockedpd/ops/expanding.py
unlockedpd/ops/fillna.py
unlockedpd/ops/pairwise.py
unlockedpd/ops/rank.py
unlockedpd/ops/rolling.py
unlockedpd/ops/stats.py
unlockedpd/ops/transform.py
unlockedpd-0.3.1.dist-info/METADATA
unlockedpd-0.3.1.dist-info/WHEEL
unlockedpd-0.3.1.dist-info/licenses/LICENSE
unlockedpd-0.3.1.dist-info/RECORD
