Metadata-Version: 2.4
Name: unlockedpd
Version: 0.3.1
Summary: Transparent pandas performance optimization via Numba-accelerated parallel operations
Project-URL: Homepage, https://github.com/Yeachan-Heo/unlockedpd
Project-URL: Documentation, https://github.com/Yeachan-Heo/unlockedpd#readme
Project-URL: Issues, https://github.com/Yeachan-Heo/unlockedpd/issues
Author: unlockedpd contributors
License-Expression: MIT
License-File: LICENSE
Keywords: numba,optimization,pandas,parallel,performance
Classifier: Development Status :: 4 - Beta
Classifier: Intended Audience :: Developers
Classifier: Intended Audience :: Science/Research
Classifier: License :: OSI Approved :: MIT License
Classifier: Operating System :: OS Independent
Classifier: Programming Language :: Python :: 3
Classifier: Programming Language :: Python :: 3.9
Classifier: Programming Language :: Python :: 3.10
Classifier: Programming Language :: Python :: 3.11
Classifier: Programming Language :: Python :: 3.12
Classifier: Topic :: Scientific/Engineering
Requires-Python: >=3.9
Requires-Dist: numba>=0.56
Requires-Dist: numpy>=1.21
Requires-Dist: packaging>=21.0
Requires-Dist: pandas<3.0,>=1.5
Provides-Extra: dev
Requires-Dist: memory-profiler>=0.60; extra == 'dev'
Requires-Dist: pytest-benchmark>=4.0; extra == 'dev'
Requires-Dist: pytest>=7.0; extra == 'dev'
